setup.py
http_request/__init__.py
http_request.egg-info/PKG-INFO
http_request.egg-info/SOURCES.txt
http_request.egg-info/dependency_links.txt
http_request.egg-info/requires.txt
http_request.egg-info/top_level.txt