Metadata-Version: 1.1
Name: http_request
Version: 1.2
Summary: A small python library to parse and build HTTP requests
Home-page: https://github.com/dennisfischer/http_request
Author: Dennis Fischer
Author-email: dennis.fischer@live.com
License: MIT
Platform: UNKNOWN
Classifier: Development Status :: 3 - Alpha
Classifier: Topic :: Utilities
Classifier: License :: OSI Approved :: MIT License
